auto_walrus.py
auto_walrus-0.3.4.dist-info/METADATA
auto_walrus-0.3.4.dist-info/WHEEL
auto_walrus-0.3.4.dist-info/entry_points.txt
auto_walrus-0.3.4.dist-info/licenses/LICENSE
auto_walrus-0.3.4.dist-info/RECORD
