Metadata-Version: 2.3
Name: auto-walrus
Version: 0.3.4
Summary: Automatically apply the awesome walrus operator
Project-URL: Homepage, https://github.com/MarcoGorelli/auto-walrus
Project-URL: Bug Tracker, https://github.com/MarcoGorelli/auto-walrus
Author-email: Marco Gorelli <33491632+MarcoGorelli@users.noreply.github.com>
License-File: LICENSE
Classifier: License :: OSI Approved :: MIT License
Classifier: Operating System :: OS Independent
Classifier: Programming Language :: Python :: 3
Requires-Python: >=3.8
Requires-Dist: tomli; python_version < '3.11'
